companion/config.py
companion/genconfig.py
companion/ipcext.py
companion/workspaces.py
companion/models/config.py
companion/utils/genconfig.py
companion/utils/general.py
companion/utils/logger.py
niri_companion-4.0.0.dist-info/licenses/LICENSE
niri_companion-4.0.0.dist-info/METADATA
niri_companion-4.0.0.dist-info/WHEEL
niri_companion-4.0.0.dist-info/entry_points.txt
niri_companion-4.0.0.dist-info/top_level.txt
niri_companion-4.0.0.dist-info/RECORD
