Metadata-Version: 2.4
Name: niri-companion
Version: 4.0.0
Summary: Niri companion scripts
Maintainer-email: Ahmet Arda Kavakcı <ahmetardakavakci@gmail.com>
License-Expression: GPL-3.0-or-later
Project-URL: Documentation, https://github.com/dybdeskarphet/niri-companion
Project-URL: Issues, https://github.com/dybdeskarphet/niri-companion/issues
Project-URL: Repository, https://github.com/dybdeskarphet/niri-companion
Project-URL: Changelog, https://github.com/dybdeskarphet/niri-companion/blob/main/CHANGELOG.md
Keywords: niri,companion,niri-companion,wayland,compositor
Requires-Python: >=3.13
License-File: LICENSE
Requires-Dist: pydantic>=2.11.7
Requires-Dist: rich>=14.1.0
Requires-Dist: tomli-w>=1.2.0
Requires-Dist: typer>=0.19.1
Requires-Dist: watchdog>=6.0.0
Dynamic: license-file
